{".class": "MypyFile", "_fullname": "matplotlib.legend", "is_partial_stub_package": false, "is_stub": true, "names": {".class": "SymbolTable", "Artist": {".class": "SymbolTableNode", "cross_ref": "matplotlib.artist.Artist", "kind": "Gdef", "module_hidden": true, "module_public": false}, "Legend": {".class": "SymbolTableNode", "kind": "Gdef", "node": {".class": "TypeInfo", "_promote": null, "abstract_attributes": [], "bases": ["matplotlib.artist.Artist"], "declared_metaclass": null, "defn": {".class": "ClassDef", "fullname": "matplotlib.legend.Legend", "name": "Legend", "type_vars": []}, "flags": [], "fullname": "matplotlib.legend.Legend", "metaclass_type": null, "metadata": {}, "module_name": "matplotlib.legend", "mro": ["matplotlib.legend.Legend", "matplotlib.artist.Artist", "builtins.object"], "names": {".class": "SymbolTable", "set_title": {".class": "SymbolTableNode", "kind": "Mdef", "node": {".class": "FuncDef", "arg_kinds": [0, 0], "arg_names": ["self", "title"], "flags": [], "fullname": "matplotlib.legend.Legend.set_title", "name": "set_title", "type": {".class": "CallableType", "arg_kinds": [0, 0], "arg_names": ["self", "title"], "arg_types": ["matplotlib.legend.Legend", "builtins.str"], "bound_args": [], "def_extras": {"first_arg": "self"}, "fallback": "builtins.function", "implicit": false, "is_ellipsis_args": false, "name": "set_title of Legend", "ret_type": {".class": "NoneType"}, "variables": []}}}}, "tuple_type": null, "type_vars": [], "typeddict_type": null}}, "__doc__": {".class": "SymbolTableNode", "kind": "Gdef", "node": {".class": "Var", "flags": ["is_ready"], "fullname": "matplotlib.legend.__doc__", "name": "__doc__", "type": "builtins.str"}}, "__file__": {".class": "SymbolTableNode", "kind": "Gdef", "node": {".class": "Var", "flags": ["is_ready"], "fullname": "matplotlib.legend.__file__", "name": "__file__", "type": "builtins.str"}}, "__name__": {".class": "SymbolTableNode", "kind": "Gdef", "node": {".class": "Var", "flags": ["is_ready"], "fullname": "matplotlib.legend.__name__", "name": "__name__", "type": "builtins.str"}}, "__package__": {".class": "SymbolTableNode", "kind": "Gdef", "node": {".class": "Var", "flags": ["is_ready"], "fullname": "matplotlib.legend.__package__", "name": "__package__", "type": "builtins.str"}}}, "path": "/opt/conda/lib/python3.7/site-packages/matplotlib-stubs/legend.pyi"}